paclair/__init__.py
paclair/__main__.py
paclair/config_reader.py
paclair/exceptions.py
paclair/handler.py
paclair/logged_object.py
paclair/struct.py
paclair/ancestries/__init__.py
paclair/ancestries/docker.py
paclair/ancestries/generic.py
paclair/api/__init__.py
paclair/api/abstract_clair_requests.py
paclair/api/clair_requests_v1.py
paclair/api/clair_requests_v3.py
paclair/api/template/report.tpl
paclair/docker/__init__.py
paclair/docker/docker_image.py
paclair/docker/docker_registry.py
paclair/plugins/__init__.py
paclair/plugins/abstract_plugin.py
paclair/plugins/docker_plugin.py
paclair/plugins/es_plugin.py
paclair/plugins/http_plugin.py
paclair_mira-0.3.dist-info/LICENSE
paclair_mira-0.3.dist-info/METADATA
paclair_mira-0.3.dist-info/WHEEL
paclair_mira-0.3.dist-info/entry_points.txt
paclair_mira-0.3.dist-info/top_level.txt
paclair_mira-0.3.dist-info/RECORD
